{"spkid": "20477519", "covariance": {"labels": ["e", "q", "tp", "node", "peri", "i"], "elements": [{"label": "e", "name": "e", "sigma": 5.64136756452862e-08, "units": null, "title": "eccentricity", "value": ".2453424611440618"}, {"value": ".9432386432181623", "title": "perihelion distance", "units": "au", "name": "q", "sigma": 7.1472742493045e-08, "label": "q"}, {"label": "tp", "units": "TDB", "title": "time of perihelion passage", "value": "2458230.389866247953", "sigma": 5.94566663575832e-05, "name": "tp"}, {"title": "longitude of the ascending node", "value": "149.9400713590568", "units": "deg", "sigma": 8.50746440074088e-06, "name": "om", "label": "node"}, {"value": "309.2587876600406", "title": "argument of perihelion", "units": "deg", "sigma": 2.65548162374972e-05, "name": "w", "label": "peri"}, {"label": "i", "sigma": 7.49391559533416e-06, "name": "i", "units": "deg", "title": "inclination", "value": "34.84013523456061"}], "data": [["3.182502799811554E-15", "-4.029244326744493E-15", "-5.399582469489989E-14", "-3.887214647835558E-15", "-1.581071016192722E-14", "9.554518051443708E-14"], ["-4.029244326744493E-15", "5.108352919477126E-15", "1.002241149910859E-13", "3.502919608765383E-15", "3.927365251091685E-14", "-1.188925630959764E-13"], ["-5.399582469489989E-14", "1.002241149910859E-13", "3.535095174356961E-9", "2.414036940843809E-10", "1.517347922950748E-9", "-2.553029435247451E-10"], ["-3.887214647835558E-15", "3.502919608765383E-15", "2.414036940843809E-10", "7.23769505298733E-11", "5.476259467349419E-11", "-3.083079929511625E-11"], ["-1.581071016192722E-14", "3.927365251091685E-14", "1.517347922950748E-9", "5.476259467349419E-11", "7.051582654072461E-10", "-9.553111206044551E-11"], ["9.554518051443708E-14", "-1.188925630959764E-13", "-2.553029435247451E-10", "-3.083079929511625E-11", "-9.553111206044551E-11", "5.615877094999255E-11"]], "epoch": "2458351.5"}, "elements": [{"label": "e", "sigma": "5.6412E-8", "name": "e", "title": "eccentricity", "value": ".245279980651094", "units": null}, {"label": "a", "sigma": "3.6657E-9", "name": "a", "title": "semi-major axis", "value": "1.249887160300374", "units": "au"}, {"label": "q", "title": "perihelion distance", "value": ".9433148618058478", "units": "au", "name": "q", "sigma": "7.1456E-8"}, {"label": "i", "units": "deg", "value": "34.84555415168017", "title": "inclination; angle with respect to x-y ecliptic plane", "name": "i", "sigma": "7.4942E-6"}, {"label": "node", "units": "deg", "title": "longitude of the ascending node", "value": "149.910308272391", "name": "om", "sigma": "8.505E-6"}, {"label": "peri", "units": "deg", "value": "309.3025820084874", "title": "argument of perihelion", "sigma": "2.6565E-5", "name": "w"}, {"value": "294.8262153704917", "title": "mean anomaly", "units": "deg", "name": "ma", "sigma": "4.4512E-5", "label": "M"}, {"title": "time of perihelion passage", "value": "2461292.900660847969", "units": "TDB", "name": "tp", "sigma": "6.3251E-5", "label": "tp"}, {"sigma": "2.2453E-6", "name": "per", "units": "d", "title": "sidereal orbital period", "value": "510.3929147948855", "label": "period"}, {"label": "n", "units": "deg/d", "title": "mean motion", "value": ".7053389448885183", "name": "n", "sigma": "3.1029E-9"}, {"units": "au", "value": "1.556459458794901", "title": "aphelion distance", "name": "ad", "sigma": "4.5648E-9", "label": "Q"}], "epoch": "2461200.5"}