{"spkid": "20531277", "covariance": {"data": [["1.8031786553178E-16", "-3.589757399740106E-16", "5.111092862316515E-14", "1.230483607806362E-13", "-8.564452146031637E-14", "1.205137267466866E-14"], ["-3.589757399740106E-16", "7.181367584013979E-16", "-9.403705316159179E-14", "-2.131422152787266E-13", "1.386689941510045E-13", "-2.276046478549845E-14"], ["5.111092862316515E-14", "-9.403705316159179E-14", "3.656947554701114E-11", "8.33194980893784E-11", "-6.967040446136234E-11", "2.179518482509337E-12"], ["1.230483607806362E-13", "-2.131422152787266E-13", "8.33194980893784E-11", "6.257666718280462E-9", "-6.24001863570485E-9", "3.43300833455084E-10"], ["-8.564452146031637E-14", "1.386689941510045E-13", "-6.967040446136234E-11", "-6.24001863570485E-9", "6.233179154698295E-9", "-3.440880525510738E-10"], ["1.205137267466866E-14", "-2.276046478549845E-14", "2.179518482509337E-12", "3.43300833455084E-10", "-3.440880525510738E-10", "2.175704776359167E-11"]], "elements": [{"label": "e", "title": "eccentricity", "value": ".6489041481376726", "units": null, "name": "e", "sigma": 1.34282487887207e-08}, {"value": ".7410048876474343", "title": "perihelion distance", "units": "au", "name": "q", "sigma": 2.679807378155e-08, "label": "q"}, {"label": "tp", "title": "time of perihelion passage", "value": "2457291.695174190307", "units": "TDB", "name": "tp", "sigma": 6.04727009046323e-06}, {"sigma": 7.91054152272805e-05, "name": "om", "units": "deg", "title": "longitude of the ascending node", "value": "246.2190833853942", "label": "node"}, {"label": "peri", "name": "w", "sigma": 7.89504854620812e-05, "value": "123.2727094302305", "title": "argument of perihelion", "units": "deg"}, {"label": "i", "name": "i", "sigma": 4.66444506491305e-06, "units": "deg", "value": "3.157740507697318", "title": "inclination"}], "labels": ["e", "q", "tp", "node", "peri", "i"], "epoch": "2457105.5"}, "elements": [{"sigma": "1.3212E-8", "name": "e", "units": null, "value": ".6481745416893107", "title": "eccentricity", "label": "e"}, {"label": "a", "units": "au", "title": "semi-major axis", "value": "2.113411607178227", "name": "a", "sigma": "1.7921E-9"}, {"label": "q", "name": "q", "sigma": "2.7377E-8", "units": "au", "value": ".7435520072946101", "title": "perihelion distance"}, {"label": "i", "name": "i", "sigma": "4.6593E-6", "units": "deg", "value": "3.184472193785258", "title": "inclination; angle with respect to x-y ecliptic plane"}, {"label": "node", "title": "longitude of the ascending node", "value": "245.3992592442439", "units": "deg", "name": "om", "sigma": "7.8381E-5"}, {"label": "peri", "sigma": "7.8268E-5", "name": "w", "units": "deg", "title": "argument of perihelion", "value": "124.2427194180063"}, {"label": "M", "sigma": "5.6423E-6", "name": "ma", "value": "173.8943737352648", "title": "mean anomaly", "units": "deg"}, {"label": "tp", "name": "tp", "sigma": "1.7128E-5", "value": "2460658.427233063107", "title": "time of perihelion passage", "units": "TDB"}, {"label": "period", "sigma": "1.4274E-6", "name": "per", "units": "d", "title": "sidereal orbital period", "value": "1122.211098067901"}, {"label": "n", "units": "deg/d", "value": ".3207952591271002", "title": "mean motion", "name": "n", "sigma": "4.0803E-10"}, {"label": "Q", "units": "au", "title": "aphelion distance", "value": "3.483271207061843", "sigma": "2.9537E-9", "name": "ad"}], "epoch": "2461200.5"}