{"spkid": "50036386", "covariance": {"epoch": "2456960.5", "data": [["1.732398038179052E-14", "-1.427859013302633E-14", "5.079699108253419E-12", "-2.13627881562393E-12", "4.963280302780354E-12", "-4.21176921464652E-13"], ["-1.427859013302633E-14", "1.176887794623755E-14", "-4.192681002124845E-12", "1.763508217702852E-12", "-4.097717179579777E-12", "3.491962096068494E-13"], ["5.079699108253419E-12", "-4.192681002124845E-12", "1.659471910708748E-9", "-7.337340335575519E-10", "1.679942650961718E-9", "-1.387475896630961E-10"], ["-2.13627881562393E-12", "1.763508217702852E-12", "-7.337340335575519E-10", "1.037656834871516E-9", "-1.460476861318164E-9", "-2.558994638612167E-12"], ["4.963280302780354E-12", "-4.097717179579777E-12", "1.679942650961718E-9", "-1.460476861318164E-9", "2.428015825313537E-9", "-7.705756584161208E-11"], ["-4.21176921464652E-13", "3.491962096068494E-13", "-1.387475896630961E-10", "-2.558994638612167E-12", "-7.705756584161208E-11", "3.982134784074683E-11"]], "elements": [{"name": "e", "sigma": 1.31620592544596e-07, "units": null, "title": "eccentricity", "value": ".4303612927448885", "label": "e"}, {"label": "q", "name": "q", "sigma": 1.08484459468799e-07, "units": "au", "title": "perihelion distance", "value": ".4643373983571033"}, {"title": "time of perihelion passage", "value": "2456963.231440969297", "units": "TDB", "sigma": 4.07366163384829e-05, "name": "tp", "label": "tp"}, {"label": "node", "sigma": 3.22126812741739e-05, "name": "om", "units": "deg", "value": "55.12811383383494", "title": "longitude of the ascending node"}, {"title": "argument of perihelion", "value": "17.92770827113884", "units": "deg", "name": "w", "sigma": 4.92749005611735e-05, "label": "peri"}, {"label": "i", "name": "i", "sigma": 6.31041582154035e-06, "value": "2.671050620511461", "title": "inclination", "units": "deg"}], "labels": ["e", "q", "tp", "node", "peri", "i"]}, "elements": [{"units": null, "title": "eccentricity", "value": ".4303942885905078", "name": "e", "sigma": "1.3189E-7", "label": "e"}, {"label": "a", "sigma": "3.0269E-9", "name": "a", "units": "au", "title": "semi-major axis", "value": ".8151426287901287"}, {"label": "q", "name": "q", "sigma": "1.0914E-7", "title": "perihelion distance", "value": ".4643098969722049", "units": "au"}, {"sigma": "6.307E-6", "name": "i", "units": "deg", "title": "inclination; angle with respect to x-y ecliptic plane", "value": "2.667671563740804", "label": "i"}, {"sigma": "3.2434E-5", "name": "om", "units": "deg", "value": "55.03592179306698", "title": "longitude of the ascending node", "label": "node"}, {"label": "peri", "units": "deg", "title": "argument of perihelion", "value": "18.02088799793745", "name": "w", "sigma": "4.9691E-5"}, {"units": "deg", "title": "mean anomaly", "value": "275.0956053186667", "sigma": "2.69E-5", "name": "ma", "label": "M"}, {"label": "tp", "value": "2461263.898138258118", "title": "time of perihelion passage", "units": "TDB", "name": "tp", "sigma": "1.9759E-5"}, {"label": "period", "title": "sidereal orbital period", "value": "268.8121134198531", "units": "d", "name": "per", "sigma": "1.4973E-6"}, {"label": "n", "sigma": "7.4595E-9", "name": "n", "value": "1.339225362354568", "title": "mean motion", "units": "deg/d"}, {"sigma": "4.3297E-9", "name": "ad", "value": "1.165975360608052", "title": "aphelion distance", "units": "au", "label": "Q"}], "epoch": "2461200.5"}