{"spkid": "50092283", "covariance": {"epoch": "2458223.5", "labels": ["e", "q", "tp", "node", "peri", "i"], "data": [["1.328911918663717E-14", "-9.965797777725173E-15", "2.1425397637706E-12", "-1.07022639606498E-12", "2.250204017376196E-12", "1.534964945945687E-13"], ["-9.965797777725173E-15", "7.473940525635983E-15", "-1.607776423628078E-12", "8.022869394226372E-13", "-1.687565595975841E-12", "-1.15437915902347E-13"], ["2.1425397637706E-12", "-1.607776423628078E-12", "4.210703722016914E-10", "-1.756846449801969E-10", "4.138387176580955E-10", "2.419602160357347E-11"], ["-1.07022639606498E-12", "8.022869394226372E-13", "-1.756846449801969E-10", "3.994762727213779E-10", "-4.967637327499321E-10", "-1.907668390344703E-11"], ["2.250204017376196E-12", "-1.687565595975841E-12", "4.138387176580955E-10", "-4.967637327499321E-10", "7.363586903155465E-10", "2.665601734881071E-11"], ["1.534964945945687E-13", "-1.15437915902347E-13", "2.419602160357347E-11", "-1.907668390344703E-11", "2.665601734881071E-11", "4.91694898167558E-11"]], "elements": [{"units": null, "value": ".5172318255013908", "title": "eccentricity", "name": "e", "sigma": 1.15278441985643e-07, "label": "e"}, {"name": "q", "sigma": 8.64519550133829e-08, "units": "au", "value": ".3602346346547194", "title": "perihelion distance", "label": "q"}, {"units": "TDB", "title": "time of perihelion passage", "value": "2458138.669584752289", "name": "tp", "sigma": 2.05199993226533e-05, "label": "tp"}, {"label": "node", "units": "deg", "title": "longitude of the ascending node", "value": "30.04385509540495", "sigma": 1.99869025294411e-05, "name": "om"}, {"units": "deg", "value": "6.381468251597211", "title": "argument of perihelion", "sigma": 2.71359298774806e-05, "name": "w", "label": "peri"}, {"title": "inclination", "value": "5.842166267773345", "units": "deg", "sigma": 7.01209596459973e-06, "name": "i", "label": "i"}]}, "elements": [{"name": "e", "sigma": "1.1532E-7", "value": ".5171110671711558", "title": "eccentricity", "units": null, "label": "e"}, {"units": "au", "value": ".7462068812697114", "title": "semi-major axis", "sigma": "1.3605E-9", "name": "a", "label": "a"}, {"sigma": "8.6456E-8", "name": "q", "value": ".360335044565871", "title": "perihelion distance", "units": "au", "label": "q"}, {"title": "inclination; angle with respect to x-y ecliptic plane", "value": "5.835353202813861", "units": "deg", "name": "i", "sigma": "7.0164E-6", "label": "i"}, {"title": "longitude of the ascending node", "value": "29.93339064744517", "units": "deg", "sigma": "1.9835E-5", "name": "om", "label": "node"}, {"label": "peri", "sigma": "2.6882E-5", "name": "w", "units": "deg", "value": "6.467622951333169", "title": "argument of perihelion"}, {"title": "mean anomaly", "value": "1.418098019691056", "units": "deg", "name": "ma", "sigma": "2.6591E-5", "label": "M"}, {"units": "TDB", "title": "time of perihelion passage", "value": "2461199.572548834934", "sigma": "1.7392E-5", "name": "tp", "label": "tp"}, {"units": "d", "title": "sidereal orbital period", "value": "235.4438231966923", "name": "per", "sigma": "6.439E-7", "label": "period"}, {"title": "mean motion", "value": "1.529027158632453", "units": "deg/d", "name": "n", "sigma": "4.1817E-9", "label": "n"}, {"label": "Q", "units": "au", "title": "aphelion distance", "value": "1.132078717973552", "name": "ad", "sigma": "2.064E-9"}], "epoch": "2461200.5"}