{"spkid": "50553178", "covariance": {"data": [["2.430618536628741E-15", "-4.824196706247394E-15", "3.624824635956079E-13", "-6.874837240147458E-13", "1.327591849297697E-12", "1.292796636010159E-13"], ["-4.824196706247394E-15", "9.575055357909508E-15", "-7.194164866483851E-13", "1.363879226847169E-12", "-2.634052958992928E-12", "-2.56497336032174E-13"], ["3.624824635956079E-13", "-7.194164866483851E-13", "7.128002737670568E-11", "-1.303417163090575E-10", "2.425630170570747E-10", "2.48118309273424E-11"], ["-6.874837240147458E-13", "1.363879226847169E-12", "-1.303417163090575E-10", "1.560136154894221E-9", "-1.768327539114539E-9", "1.58532891807076E-10"], ["1.327591849297697E-12", "-2.634052958992928E-12", "2.425630170570747E-10", "-1.768327539114539E-9", "2.162323757086295E-9", "-1.186150954115141E-10"], ["1.292796636010159E-13", "-2.56497336032174E-13", "2.48118309273424E-11", "1.58532891807076E-10", "-1.186150954115141E-10", "4.249937236867103E-11"]], "elements": [{"label": "e", "title": "eccentricity", "value": ".6166853743447172", "units": null, "sigma": 4.93013035996893e-08, "name": "e"}, {"sigma": 9.78522118191996e-08, "name": "q", "units": "au", "title": "perihelion distance", "value": ".7452877228118456", "label": "q"}, {"name": "tp", "sigma": 8.44274998899681e-06, "title": "time of perihelion passage", "value": "2458453.886807131281", "units": "TDB", "label": "tp"}, {"sigma": 3.94985588964233e-05, "name": "om", "units": "deg", "value": "264.9595091780919", "title": "longitude of the ascending node", "label": "node"}, {"value": "87.63933211890723", "title": "argument of perihelion", "units": "deg", "sigma": 4.65007930801862e-05, "name": "w", "label": "peri"}, {"name": "i", "sigma": 6.5191542678994e-06, "units": "deg", "title": "inclination", "value": "2.281295075951719", "label": "i"}], "labels": ["e", "q", "tp", "node", "peri", "i"], "epoch": "2458490.5"}, "elements": [{"label": "e", "name": "e", "sigma": "4.9815E-8", "units": null, "title": "eccentricity", "value": ".616907005123533"}, {"value": "1.943116768434264", "title": "semi-major axis", "units": "au", "sigma": "9.5146E-9", "name": "a", "label": "a"}, {"label": "q", "title": "perihelion distance", "value": ".7443944222141646", "units": "au", "name": "q", "sigma": "9.665E-8"}, {"units": "deg", "value": "2.227620013198288", "title": "inclination; angle with respect to x-y ecliptic plane", "sigma": "6.5878E-6", "name": "i", "label": "i"}, {"name": "om", "sigma": "4.0913E-5", "units": "deg", "value": "264.4974478089796", "title": "longitude of the ascending node", "label": "node"}, {"units": "deg", "title": "argument of perihelion", "value": "88.11567000159127", "name": "w", "sigma": "4.7325E-5", "label": "peri"}, {"units": "deg", "title": "mean anomaly", "value": "279.1624207804347", "name": "ma", "sigma": "5.3053E-6", "label": "M"}, {"name": "tp", "sigma": "1.6121E-5", "value": "2461422.655758496890", "title": "time of perihelion passage", "units": "TDB", "label": "tp"}, {"name": "per", "sigma": "7.2666E-6", "value": "989.3427516137639", "title": "sidereal orbital period", "units": "d", "label": "period"}, {"label": "n", "title": "mean motion", "value": ".3638779375628789", "units": "deg/d", "sigma": "2.6726E-9", "name": "n"}, {"name": "ad", "sigma": "1.5384E-8", "title": "aphelion distance", "value": "3.141839114654364", "units": "au", "label": "Q"}], "epoch": "2461200.5"}