{"spkid": "50667150", "covariance": {"epoch": "2457592.5", "data": [["8.417152149685067E-14", "-1.601324832644635E-13", "1.255812717721435E-11", "-1.991330553756559E-12", "-1.168228689591107E-12", "-1.202820871950189E-12"], ["-1.601324832644635E-13", "3.070362535617878E-13", "-1.884389492217354E-11", "3.662653680034121E-12", "3.453814041631604E-12", "2.148502935908088E-12"], ["1.255812717721435E-11", "-1.884389492217354E-11", "1.290430242188297E-8", "-5.853984795962081E-10", "2.620249872924861E-9", "-5.077225569066222E-10"], ["-1.991330553756559E-12", "3.662653680034121E-12", "-5.853984795962081E-10", "3.800695812360075E-10", "-3.5825863704972E-10", "1.908563162461809E-12"], ["-1.168228689591107E-12", "3.453814041631604E-12", "2.620249872924861E-9", "-3.5825863704972E-10", "1.072707854388607E-9", "-4.209656682666319E-11"], ["-1.202820871950189E-12", "2.148502935908088E-12", "-5.077225569066222E-10", "1.908563162461809E-12", "-4.209656682666319E-11", "1.365775627962533E-10"]], "elements": [{"units": null, "value": ".5207901806594858", "title": "eccentricity", "name": "e", "sigma": 2.90123286719372e-07, "label": "e"}, {"units": "au", "title": "perihelion distance", "value": ".9061965761632261", "sigma": 5.54108521466497e-07, "name": "q", "label": "q"}, {"title": "time of perihelion passage", "value": "2457612.822533303188", "units": "TDB", "sigma": 0.000113597105693248, "name": "tp", "label": "tp"}, {"title": "longitude of the ascending node", "value": "223.5447571039679", "units": "deg", "name": "om", "sigma": 1.94953733289724e-05, "label": "node"}, {"label": "peri", "units": "deg", "value": "231.9193998164542", "title": "argument of perihelion", "name": "w", "sigma": 3.2752219075791e-05}, {"value": "19.18683002483693", "title": "inclination", "units": "deg", "name": "i", "sigma": 1.1686640355391e-05, "label": "i"}], "labels": ["e", "q", "tp", "node", "peri", "i"]}, "elements": [{"label": "e", "value": ".5207022733802915", "title": "eccentricity", "units": null, "name": "e", "sigma": "2.8929E-7"}, {"label": "a", "name": "a", "sigma": "1.0111E-7", "units": "au", "value": "1.891200407164559", "title": "semi-major axis"}, {"label": "q", "sigma": "5.5263E-7", "name": "q", "title": "perihelion distance", "value": ".9064480557362401", "units": "au"}, {"sigma": "1.1692E-5", "name": "i", "units": "deg", "title": "inclination; angle with respect to x-y ecliptic plane", "value": "19.15999569540694", "label": "i"}, {"units": "deg", "value": "223.3662539219549", "title": "longitude of the ascending node", "name": "om", "sigma": "1.9588E-5", "label": "node"}, {"name": "w", "sigma": "3.2906E-5", "value": "232.1464298080891", "title": "argument of perihelion", "units": "deg", "label": "peri"}, {"label": "M", "units": "deg", "title": "mean anomaly", "value": "279.520656804587", "sigma": ".00014917", "name": "ma"}, {"sigma": ".00041051", "name": "tp", "units": "TDB", "value": "2461412.866827141986", "title": "time of perihelion passage", "label": "tp"}, {"label": "period", "title": "sidereal orbital period", "value": "949.9587687424403", "units": "d", "sigma": "7.6185E-5", "name": "per"}, {"label": "n", "value": ".3789638159523172", "title": "mean motion", "units": "deg/d", "name": "n", "sigma": "3.0392E-8"}, {"label": "Q", "name": "ad", "sigma": "1.5376E-7", "value": "2.875952758592877", "title": "aphelion distance", "units": "au"}], "epoch": "2461200.5"}