{"spkid": "50841213", "covariance": {"elements": [{"sigma": 4.28513464182247e-06, "name": "e", "units": null, "title": "eccentricity", "value": ".2023379107229205", "label": "e"}, {"label": "q", "name": "q", "sigma": 5.31789001648967e-06, "value": ".9604579802301088", "title": "perihelion distance", "units": "au"}, {"label": "tp", "value": "2459808.875645873024", "title": "time of perihelion passage", "units": "TDB", "sigma": 0.00174225731605469, "name": "tp"}, {"label": "node", "name": "om", "sigma": 3.21433530577196e-05, "value": "19.26108502361153", "title": "longitude of the ascending node", "units": "deg"}, {"sigma": 0.000925619955112007, "name": "w", "title": "argument of perihelion", "value": "12.3513010331466", "units": "deg", "label": "peri"}, {"name": "i", "sigma": 0.000293224406892144, "units": "deg", "value": "23.58736000184929", "title": "inclination", "label": "i"}], "data": [["1.836237889854696E-11", "-2.278784981840676E-11", "5.050962173754211E-9", "1.253328196219513E-10", "2.83808929364779E-9", "1.19318678576751E-9"], ["-2.278784981840676E-11", "2.827995422748047E-11", "-6.26197318864112E-9", "-1.555437449484601E-10", "-3.518926418868907E-9", "-1.480290133869475E-9"], ["5.050962173754211E-9", "-6.26197318864112E-9", "3.035460555346097E-6", "3.261187367234073E-8", "1.610125120473912E-6", "4.454451191500362E-7"], ["1.253328196219513E-10", "-1.555437449484601E-10", "3.261187367234073E-8", "1.033195145793211E-9", "1.827108143361951E-8", "8.090774760642386E-9"], ["2.83808929364779E-9", "-3.518926418868907E-9", "1.610125120473912E-6", "1.827108143361951E-8", "8.567723013015535E-7", "2.434085766036109E-7"], ["1.19318678576751E-9", "-1.480290133869475E-9", "4.454451191500362E-7", "8.090774760642386E-9", "2.434085766036109E-7", "8.598055279724965E-8"]], "labels": ["e", "q", "tp", "node", "peri", "i"], "epoch": "2459766.5"}, "elements": [{"value": ".2022499135220425", "title": "eccentricity", "units": null, "sigma": "4.2848E-6", "name": "e", "label": "e"}, {"sigma": "1.9893E-7", "name": "a", "value": "1.204058672121999", "title": "semi-major axis", "units": "au", "label": "a"}, {"name": "q", "sigma": "5.3177E-6", "value": ".9605379098098591", "title": "perihelion distance", "units": "au", "label": "q"}, {"units": "deg", "value": "23.58527215738613", "title": "inclination; angle with respect to x-y ecliptic plane", "name": "i", "sigma": ".0002932", "label": "i"}, {"units": "deg", "value": "19.25059508656981", "title": "longitude of the ascending node", "name": "om", "sigma": "3.221E-5", "label": "node"}, {"label": "peri", "units": "deg", "title": "argument of perihelion", "value": "12.3697819284325", "sigma": ".00092651", "name": "w"}, {"name": "ma", "sigma": ".0011478", "units": "deg", "title": "mean anomaly", "value": "318.1323777225336", "label": "M"}, {"label": "tp", "title": "time of perihelion passage", "value": "2461256.623622977740", "units": "TDB", "sigma": ".0015314", "name": "tp"}, {"value": "482.5806475965211", "title": "sidereal orbital period", "units": "d", "name": "per", "sigma": ".0001196", "label": "period"}, {"name": "n", "sigma": "1.8488E-7", "value": ".7459893010483729", "title": "mean motion", "units": "deg/d", "label": "n"}, {"name": "ad", "sigma": "2.3917E-7", "units": "au", "title": "aphelion distance", "value": "1.447579434434138", "label": "Q"}], "epoch": "2461200.5"}