{"spkid": "54054526", "covariance": {"epoch": "2459623.5", "elements": [{"label": "e", "name": "e", "sigma": 6.20739781098011e-08, "value": ".3909221167410105", "title": "eccentricity", "units": null}, {"name": "q", "sigma": 7.92861685449238e-08, "title": "perihelion distance", "value": ".7946500864715234", "units": "au", "label": "q"}, {"label": "tp", "name": "tp", "sigma": 2.52476167934627e-05, "units": "TDB", "title": "time of perihelion passage", "value": "2459580.048842132503"}, {"value": "359.4125861681219", "title": "longitude of the ascending node", "units": "deg", "sigma": 3.17293805635676e-06, "name": "om", "label": "node"}, {"label": "peri", "sigma": 1.3206299292614e-05, "name": "w", "value": "262.1008826595682", "title": "argument of perihelion", "units": "deg"}, {"name": "i", "sigma": 1.52089634702998e-05, "units": "deg", "value": "44.2142571621029", "title": "inclination", "label": "i"}], "data": [["3.853178758376061E-15", "-4.916184193870293E-15", "1.120569385578875E-12", "-2.064097127998427E-15", "3.237539220084053E-13", "-3.512198428310462E-13"], ["-4.916184193870293E-15", "6.286296522534057E-15", "-1.380526591495948E-12", "2.848401413516821E-15", "-3.8391198338916E-13", "4.357078871590613E-13"], ["1.120569385578875E-12", "-1.380526591495948E-12", "6.374421537495384E-10", "2.999131332570579E-12", "3.000091088877652E-10", "-1.771465806281918E-10"], ["-2.064097127998427E-15", "2.848401413516821E-15", "2.999131332570579E-12", "1.006753590947699E-11", "-5.371531918049346E-12", "-1.078192251752268E-11"], ["3.237539220084053E-13", "-3.8391198338916E-13", "3.000091088877652E-10", "-5.371531918049346E-12", "1.744063410060963E-10", "-7.149155387381748E-11"], ["-3.512198428310462E-13", "4.357078871590613E-13", "-1.771465806281918E-10", "-1.078192251752268E-11", "-7.149155387381748E-11", "2.313125698409143E-10"]], "labels": ["e", "q", "tp", "node", "peri", "i"]}, "elements": [{"label": "e", "name": "e", "sigma": "6.2022E-8", "units": null, "value": ".3909912391254604", "title": "eccentricity"}, {"units": "au", "title": "semi-major axis", "value": "1.304654545259581", "name": "a", "sigma": "6.6981E-9", "label": "a"}, {"label": "q", "sigma": "7.9287E-8", "name": "q", "units": "au", "title": "perihelion distance", "value": ".7945460479778732"}, {"sigma": "1.5207E-5", "name": "i", "units": "deg", "value": "44.21110709093102", "title": "inclination; angle with respect to x-y ecliptic plane", "label": "i"}, {"label": "node", "units": "deg", "title": "longitude of the ascending node", "value": "359.3879103869879", "name": "om", "sigma": "3.1704E-6"}, {"title": "argument of perihelion", "value": "262.0889179824873", "units": "deg", "name": "w", "sigma": "1.3221E-5", "label": "peri"}, {"label": "M", "sigma": "2.3779E-5", "name": "ma", "title": "mean anomaly", "value": "351.8360608290372", "units": "deg"}, {"label": "tp", "name": "tp", "sigma": "3.6038E-5", "title": "time of perihelion passage", "value": "2461212.843518824802", "units": "TDB"}, {"label": "period", "name": "per", "sigma": "4.1917E-6", "units": "d", "title": "sidereal orbital period", "value": "544.3042487055549"}, {"label": "n", "value": ".6613948005295555", "title": "mean motion", "units": "deg/d", "name": "n", "sigma": "5.0934E-9"}, {"name": "ad", "sigma": "9.317E-9", "title": "aphelion distance", "value": "1.814763042541288", "units": "au", "label": "Q"}], "epoch": "2461200.5"}